LICENSE
MANIFEST.in
README.rst
setup.cfg
setup.py
aapg/__init__.py
aapg/args_generator.py
aapg/asm_templates.py
aapg/asm_writer.py
aapg/constants.py
aapg/gen_random_program.py
aapg/isa_funcs.py
aapg/log.py
aapg/main.py
aapg/mappings.py
aapg/program_generator.py
aapg/requirements.txt
aapg/setup_self_check.py
aapg/utils.py
aapg.egg-info/PKG-INFO
aapg.egg-info/SOURCES.txt
aapg.egg-info/dependency_links.txt
aapg.egg-info/entry_points.txt
aapg.egg-info/not-zip-safe
aapg.egg-info/requires.txt
aapg.egg-info/top_level.txt
aapg/env/__init__.py
aapg/env/comments.py
aapg/env/config.py
aapg/env/encoding.py
aapg/env/env_setup.py
aapg/env/illegal_perl.py
aapg/env/linker.py
aapg/env/make.py
aapg/env/prelude.py
aapg/env/templates.py
tests/__init__.py
tests/test_BasicGenerator.py
tests/test_aapg.py
tests/test_aapg2.py